catvox/__init__.py
catvox/args.py
catvox/main.py
catvox/input/__init__.py
catvox/input/sounddevice.py
catvox/input/sources.py
catvox/stream/__init__.py
catvox/transcribe/__init__.py
catvox/transcribe/whisper.py
catvox/utils/__init__.py
catvox/utils/classproperty.py
catvox/utils/monkeypipe.py
catvox-0.1.3.dist-info/entry_points.txt
catvox-0.1.3.dist-info/WHEEL
catvox-0.1.3.dist-info/METADATA
catvox-0.1.3.dist-info/RECORD
